lact/__init__.py
lact/browser.py
lact/case.py
lact/data.py
lact/entity.py
lact/helper.py
lact/helper_test.py
lact/logger.py
lact/request.py
lact-0.7.4.dist-info/METADATA
lact-0.7.4.dist-info/WHEEL
lact-0.7.4.dist-info/top_level.txt
lact-0.7.4.dist-info/RECORD
