Metadata-Version: 2.1
Name: lact
Version: 0.7.4
Summary: free automation testing tool powered by python
Home-page: UNKNOWN
Author: Linty Liu Tingli
Author-email: liu.tingli@outlook.com
License: GNU GPLv3
Platform: UNKNOWN
Classifier: Topic :: Software Development :: Libraries :: Python Modules
Classifier: Programming Language :: Python
Classifier: Programming Language :: Python :: 3
Classifier: Programming Language :: Python :: 3.5
Classifier: Programming Language :: Python :: 3.6
Classifier: Programming Language :: Python :: 3.7
Classifier: Programming Language :: Python :: 3.8
Classifier: Programming Language :: Python :: 3.9
Classifier: Programming Language :: Python :: Implementation :: CPython
Requires-Dist: pytest (>=5.2.2)
Requires-Dist: requests (>=2.21.0)
Requires-Dist: pymysql (>=0.9.3)
Requires-Dist: pyyaml (>=5.1.2)
Requires-Dist: allure-pytest (>=2.6.3)
Requires-Dist: pytest-html (>=1.20.0)
Requires-Dist: pytest-rerunfailures (>=7.0)
Requires-Dist: pycryptodome (>=3.9.1)
Requires-Dist: lxml (>=4.4.0)
Requires-Dist: beautifulsoup4 (>=4.8.1)
Requires-Dist: coverage (>=4.5.1)
Requires-Dist: pillow (>=6.2.1)
Requires-Dist: pytesseract (>=0.3.1)
Requires-Dist: urllib3 (>=1.24.2)
Requires-Dist: selenium (>=3.141.0)
Requires-Dist: loguru (>=0.5.1)
Requires-Dist: jsonpath (>=0.82)
